CHANGES.rst
LICENSE
MANIFEST.in
README.rst
setup.cfg
setup.py
django_p3p.egg-info/PKG-INFO
django_p3p.egg-info/SOURCES.txt
django_p3p.egg-info/dependency_links.txt
django_p3p.egg-info/not-zip-safe
django_p3p.egg-info/requires.txt
django_p3p.egg-info/top_level.txt
p3p/__init__.py
p3p/middleware.py
p3p/models.py
p3p/urls.py
p3p/views.py
p3p/templates/p3p/headers.txt
p3p/templates/p3p/p3p.xml
p3p/templates/p3p/policy.p3p
p3p/tests/__init__.py
p3p/tests/test_middleware.py
p3p/tests/test_urls.py
p3p/tests/test_views.py
p3p/tests/urls.py