Metadata-Version: 1.1
Name: django-p3p
Version: 1.1.0
Summary: Django P3P makes it easier to set
Home-page: http://github.com/jjanssen/django-p3p
Author: Janneke Janssen
Author-email: j.janssen@lukkien.com
License: Apache License, Version 2.0
Keywords: session patch middleware django
Platform: UNKNOWN
Classifier: Development Status :: 5 - Production/Stable
Classifier: Environment :: Web Environment
Classifier: Framework :: Django
Classifier: Intended Audience :: Developers
Classifier: License :: OSI Approved :: Apache Software License
Classifier: Operating System :: MacOS :: MacOS X
Classifier: Operating System :: POSIX
Classifier: Programming Language :: Python
Classifier: Programming Language :: Python :: 2.6
Classifier: Topic :: Internet :: WWW/HTTP :: Browsers
Classifier: Topic :: Internet :: WWW/HTTP :: Session
Requires: Django (>=1.5)
